ipfs_pin_steem-1.0.7.dist-info/DESCRIPTION.rst
ipfs_pin_steem-1.0.7.dist-info/METADATA
ipfs_pin_steem-1.0.7.dist-info/RECORD
ipfs_pin_steem-1.0.7.dist-info/WHEEL
ipfs_pin_steem-1.0.7.dist-info/entry_points.txt
ipfs_pin_steem-1.0.7.dist-info/metadata.json
ipfs_pin_steem-1.0.7.dist-info/top_level.txt
ipfs_pin_steem-1.0.7.dist-info/zip-safe
ipfspinsteem/__init__.py
ipfspinsteem/ipfspinsteem2.py
ipfspinsteem/strings.py
ipfspinsteem/__pycache__/__init__.cpython-36.pyc
ipfspinsteem/__pycache__/ipfspinsteem2.cpython-36.pyc
ipfspinsteem/__pycache__/strings.cpython-36.pyc
