Metadata-Version: 2.0
Name: ipfs-pin-steem
Version: 1.0.7
Summary: Creates an object of all Hashes given from a dtube/dsound/dlive URL and pins it to an IPFS Node
Home-page: UNKNOWN
License: Unlicensed
Keywords: ipfs steem dtube dsound dlive
Platform: UNKNOWN
Classifier: Programming Language :: Python :: 3.6
Provides-Extra: beem
Provides-Extra: steem
Requires-Dist: ipfsapi
Provides-Extra: beem
Requires-Dist: beem; extra == 'beem'
Provides-Extra: steem
Requires-Dist: steem; extra == 'steem'
